ColabTurtleArbreBinaire.py
ColabTurtleArbreBinaire-0.0.4.dist-info/LICENSE
ColabTurtleArbreBinaire-0.0.4.dist-info/METADATA
ColabTurtleArbreBinaire-0.0.4.dist-info/WHEEL
ColabTurtleArbreBinaire-0.0.4.dist-info/top_level.txt
ColabTurtleArbreBinaire-0.0.4.dist-info/RECORD
