Metadata-Version: 2.1
Name: ColabTurtleArbreBinaire
Version: 0.0.4
Summary: A module using ColabTurtlePlus to draw binary trees
Author-email: Matthieu Bensussan <matthieu.bensussan@gmail.com>
Classifier: Programming Language :: Python :: 3
Classifier: License :: OSI Approved :: MIT License
Classifier: Operating System :: OS Independent
Requires-Python: >=3.7
License-File: LICENSE
Requires-Dist: ColabTurtlePlus
